Metadata-Version: 2.1
Name: snapshot
Version: 0.1.1
Summary: Extract named tuples from classes with a simple descriptor
Home-page: https://github.com/gemerden/snapshot
Author: Lars van Gemerden
Author-email: gemerden@gmail.com
License: MIT License
Keywords: namedtuple transform object descriptor utility performance
Platform: UNKNOWN
Classifier: Development Status :: 4 - Beta
Classifier: Intended Audience :: Developers
Classifier: Topic :: Software Development
Classifier: License :: OSI Approved :: MIT License
Classifier: Programming Language :: Python :: 3.6
Classifier: Programming Language :: Python :: 3.7
Classifier: Programming Language :: Python :: 3.8
Classifier: Programming Language :: Python :: 3.9
Requires-Python: >=3.6
License-File: LICENSE
